MooCoderPy/ScrollText.py
MooCoderPy/SettingsDialog.py
MooCoderPy/TerminalWindow.py
MooCoderPy/__init__.py
MooCoderPy/__main__.py
MooCoderPy/codetext.py
MooCoderPy/connections.py
MooCoderPy/findreplacedialog.py
MooCoderPy/moocoder.ico
MooCoderPy/moocoder.png
MooCoderPy/moocoder_64.png
MooCoderPy/mydialogs.py
MooCoderPy/splitlist.py
MooCoderPy/testtk.py
MooCoderPy/wgplib.py
MooCoderPy/img/icons8-code-24.png
MooCoderPy/img/icons8-document-24.png
MooCoderPy/img/icons8-edit-24.png
MooCoderPy/img/icons8-edit-property-24.png
MooCoderPy/img/icons8-inspect-code-24.png
MooCoderPy/img/icons8-monitor-24.png
MooCoderPy/img/icons8-new-property-24.png
MooCoderPy/img/icons8-spiral-bound-booklet-24.png
MooCoderPy_rjmatthews62-0.5.9.dist-info/LICENSE
MooCoderPy_rjmatthews62-0.5.9.dist-info/METADATA
MooCoderPy_rjmatthews62-0.5.9.dist-info/WHEEL
MooCoderPy_rjmatthews62-0.5.9.dist-info/top_level.txt
MooCoderPy_rjmatthews62-0.5.9.dist-info/RECORD
