Metadata-Version: 2.1
Name: MooCoderPy-rjmatthews62
Version: 0.5.9
Summary: Coding IDE/Client for LambdaMOO style servers
Home-page: https://github.com/rjmatthews62/MooCoderPy
Author: Robbie Matthews
Author-email: robbie@mithril.com.au
Project-URL: Bug Tracker, https://github.com/rjmatthews62/MooCoderPy/issues
Classifier: Programming Language :: Python :: 3
Classifier: License :: OSI Approved :: MIT License
Classifier: Operating System :: OS Independent
Requires-Python: >=3.6
License-File: LICENSE
Requires-Dist: mudtelnet
